{"status":{"lastIngestionAt":"2026-04-16T16:12:10.558Z","lastPricingRefreshAt":"2026-04-16T15:00:09.453Z","nextPricingRefreshAt":"2026-04-16T18:00:00.000Z","marketSessionState":"open"},"pricingRefreshHoursUtc":[15,18,21],"targetRefreshRunsPerTradingDay":3,"alerts":{"launchState":"deferred","deliveryMode":"deferred","mvpStatus":"deferred-from-launch","subscriptionsApiEnabled":false,"workerDispatchEnabled":false,"message":"Alert delivery is deferred from launch until provider-backed delivery is implemented and validated."},"demoData":{"mode":"deterministic-fallback","counts":{"verifiedTransactions":3,"verifiedHoldingSnapshots":2,"verifiedMembers":2,"verifiedAssets":2,"demoSeedTransactions":3,"officialTransactions":0}},"healthSignals":{"pendingAlertEventCount":0,"minutesSinceLastIngestion":27,"minutesSinceLastPricingRefresh":99,"minutesSinceLastSuccessfulAlertDispatch":null},"latestIngestionRun":{"runId":"73f04014-7e0d-4d8d-acda-b6ca71c744b5","mode":"hourly","sourceSystem":"official-ptr","cursorKey":"hourly:2019-2026","fromYear":2019,"toYear":2026,"startedAt":"2026-04-16T16:12:03.727Z","finishedAt":"2026-04-16T16:12:10.561Z","success":true,"failureReason":null,"fetchedDocuments":0,"parsedDocuments":0,"quarantinedDocuments":0,"extractedTransactions":0,"provenanceCoverageRatio":0,"warnings":["senate-fetch-failure:Error: HTTP 403 for https://efdsearch.senate.gov/search/report/data/"]},"latestPricingRefreshRun":{"runId":"80ed1d23-c951-49db-ba0d-c1c29e6c04d6","workerName":"pricing-refresh","startedAt":"2026-04-16T15:00:09.000Z","finishedAt":"2026-04-16T15:00:11.000Z","success":true,"failureReason":null,"metrics":{"assetsUpdated":0,"assetsConsidered":2,"skippedTickerCount":2},"warnings":["Skipped market price refresh for 2 ticker(s): AMZN, MSFT"]},"latestAlertWorkerRun":null}